psycopg2/__init__.py
psycopg2/_ipaddress.py
psycopg2/_json.py
psycopg2/_psycopg.cp310-win32.pyd
psycopg2/_psycopg.cp310-win_amd64.pyd
psycopg2/_psycopg.cp36-win32.pyd
psycopg2/_psycopg.cp36-win_amd64.pyd
psycopg2/_psycopg.cp37-win32.pyd
psycopg2/_psycopg.cp37-win_amd64.pyd
psycopg2/_psycopg.cp38-win32.pyd
psycopg2/_psycopg.cp38-win_amd64.pyd
psycopg2/_psycopg.cp39-win32.pyd
psycopg2/_psycopg.cp39-win_amd64.pyd
psycopg2/_psycopg.cpython-310-aarch64-linux-gnu.so
psycopg2/_psycopg.cpython-310-darwin.so
psycopg2/_psycopg.cpython-310-i386-linux-gnu.so
psycopg2/_psycopg.cpython-310-powerpc64le-linux-gnu.so
psycopg2/_psycopg.cpython-310-x86_64-linux-gnu.so
psycopg2/_psycopg.cpython-36m-aarch64-linux-gnu.so
psycopg2/_psycopg.cpython-36m-darwin.so
psycopg2/_psycopg.cpython-36m-i386-linux-gnu.so
psycopg2/_psycopg.cpython-36m-powerpc64le-linux-gnu.so
psycopg2/_psycopg.cpython-36m-x86_64-linux-gnu.so
psycopg2/_psycopg.cpython-37m-aarch64-linux-gnu.so
psycopg2/_psycopg.cpython-37m-darwin.so
psycopg2/_psycopg.cpython-37m-i386-linux-gnu.so
psycopg2/_psycopg.cpython-37m-powerpc64le-linux-gnu.so
psycopg2/_psycopg.cpython-37m-x86_64-linux-gnu.so
psycopg2/_psycopg.cpython-38-aarch64-linux-gnu.so
psycopg2/_psycopg.cpython-38-darwin.so
psycopg2/_psycopg.cpython-38-i386-linux-gnu.so
psycopg2/_psycopg.cpython-38-powerpc64le-linux-gnu.so
psycopg2/_psycopg.cpython-38-x86_64-linux-gnu.so
psycopg2/_psycopg.cpython-39-aarch64-linux-gnu.so
psycopg2/_psycopg.cpython-39-darwin.so
psycopg2/_psycopg.cpython-39-i386-linux-gnu.so
psycopg2/_psycopg.cpython-39-powerpc64le-linux-gnu.so
psycopg2/_psycopg.cpython-39-x86_64-linux-gnu.so
psycopg2/_range.py
psycopg2/errorcodes.py
psycopg2/errors.py
psycopg2/extensions.py
psycopg2/extras.py
psycopg2/pool.py
psycopg2/sql.py
psycopg2/tz.py
psycopg2/.dylibs/libcom_err.3.0.dylib
psycopg2/.dylibs/libcrypto.1.1.dylib
psycopg2/.dylibs/libgssapi_krb5.2.2.dylib
psycopg2/.dylibs/libk5crypto.3.1.dylib
psycopg2/.dylibs/libkrb5.3.3.dylib
aws_lambda_compatible_psycopg2-1.0.0.dist-info/METADATA
aws_lambda_compatible_psycopg2-1.0.0.dist-info/WHEEL
aws_lambda_compatible_psycopg2-1.0.0.dist-info/top_level.txt
aws_lambda_compatible_psycopg2-1.0.0.dist-info/RECORD
